delay.py
setup.py
findDelayAshwin.egg-info/PKG-INFO
findDelayAshwin.egg-info/SOURCES.txt
findDelayAshwin.egg-info/dependency_links.txt
findDelayAshwin.egg-info/top_level.txt