Metadata-Version: 1.0
Name: findDelayAshwin
Version: 1.0.0
Summary: an API to print list recursively
Home-page: UNKNOWN
Author: Ashwin
Author-email: ashwinjoseph95@gmail.com
License: UNKNOWN
Platform: UNKNOWN
